pycnet_devkit/__init__.py
pycnet_devkit/altair/__init__.py
pycnet_devkit/flask/__init__.py
pycnet_devkit/flask/html.py
pycnet_devkit/flask/support.py
pycnet_devkit/google_signin/__init__.py
pycnet_devkit/google_signin/code.py
pycnet_devkit/google_signin/support.py
pycnet_devkit/gsheet/__init__.py
pycnet_devkit/gsheet/code.py
pycnet_devkit/mysql/__init__.py
pycnet_devkit/mysql/pull.py
pycnet_devkit/mysql/query.py
pycnet_devkit/subj/__init__.py
pycnet_devkit/subj/code.py
pycnet_devkit-0.0.3.dist-info/LICENSE
pycnet_devkit-0.0.3.dist-info/METADATA
pycnet_devkit-0.0.3.dist-info/WHEEL
pycnet_devkit-0.0.3.dist-info/top_level.txt
pycnet_devkit-0.0.3.dist-info/RECORD
