Metadata-Version: 2.1
Name: pycnet-devkit
Version: 0.0.3
Summary: A personal package
Home-page: https://github.com
Author: spyc
Author-email: unknown@gmail.com
License: MIT
Platform: UNKNOWN
Classifier: Programming Language :: Python :: 3
Classifier: License :: OSI Approved :: MIT License
Classifier: Operating System :: OS Independent
Requires-Dist: pandas
Requires-Dist: pandas-flavor
